sd_server/__init__.py
sd_server/diffusers_client.py
sd_server/diffusers_server.py
sd_server-0.1.0.dist-info/LICENSE
sd_server-0.1.0.dist-info/METADATA
sd_server-0.1.0.dist-info/WHEEL
sd_server-0.1.0.dist-info/top_level.txt
sd_server-0.1.0.dist-info/RECORD
