Metadata-Version: 2.1
Name: sd-server
Version: 0.1.0
Summary: Stable Diffusion server built with FastAPI
Home-page: https://github.com/shyamsn97/stable-diffusion-server
Author: Shyam Sudhakaran
Author-email: shyamsnair@protonmail.com
License: MIT
Platform: UNKNOWN
Classifier: Development Status :: 2 - Pre-Alpha
Classifier: License :: OSI Approved :: MIT License
Classifier: Programming Language :: Python :: 3
License-File: LICENSE
Requires-Dist: fastapi
Requires-Dist: pyngrok
Requires-Dist: nest-asyncio
Requires-Dist: uvicorn
Requires-Dist: starlette (==0.20.4)
Requires-Dist: pillow
Requires-Dist: numpy
Requires-Dist: diffusers
Requires-Dist: transformers
Requires-Dist: torch
Requires-Dist: accelerate
